pennylane_ionq/__init__.py
pennylane_ionq/_version.py
pennylane_ionq/api_client.py
pennylane_ionq/device.py
pennylane_ionq/exceptions.py
pennylane_ionq/ops.py
pennylane_ionq-0.43.0.dist-info/licenses/LICENSE
pennylane_ionq-0.43.0.dist-info/METADATA
pennylane_ionq-0.43.0.dist-info/WHEEL
pennylane_ionq-0.43.0.dist-info/entry_points.txt
pennylane_ionq-0.43.0.dist-info/top_level.txt
pennylane_ionq-0.43.0.dist-info/RECORD
